MANIFEST.in
README.md
setup.py
bottle_haml.egg-info/PKG-INFO
bottle_haml.egg-info/SOURCES.txt
bottle_haml.egg-info/dependency_links.txt
bottle_haml.egg-info/requires.txt
bottle_haml.egg-info/top_level.txt
bottlehaml/__init__.py