Metadata-Version: 1.0
Name: bottle-haml
Version: 0.1.4
Summary: UNKNOWN
Home-page: https://github.com/wireload/bottle-haml
Author: Zachary Jones
Author-email: me@zacharytamas.com
License: BSD
Platform: UNKNOWN
